[
  {
    "id": 1,
    "nombre": "WILLIAMSON ",
    "cargo": "Gerente General",
    "imagen": "https://JhonFlorez17.github.io/Juventic-3/images/stuff-img-01.jpg"
  },
  {
    "id": 2,
    "nombre": "STEVE THOMAS ",
    "cargo": "Chef",
    "imagen": "https://JhonFlorez17.github.io/Juventic-3/images/stuff-img-02.jpg"
  },
  {
    "id": 3,
    "nombre": "KRISTIANA",
    "cargo": "Panadera",
    "imagen": "https://JhonFlorez17.github.io/Juventic-3/images/stuff-img-03.jpg"
  },
  {
    "id": 4,
    "nombre": "DOUGLAS",
    "cargo": "Chef",
    "imagen": "https://JhonFlorez17.github.io/Juventic-3/images/stuff-img-04.jpg"
  },
  {
    "id": 5,
    "nombre": "MICHELL",
    "cargo": "Auxiliar De Cocina",
    "imagen": "https://JhonFlorez17.github.io/Juventic-3/images/stuff-img-05.jpg"
  },
  {
    "id": 6,
    "nombre": "DANNY",
    "cargo": "Auxiliar De Cocina",
    "imagen": "https://JhonFlorez17.github.io/Juventic-3/images/stuff-img-06.jpg"
  }
]
